zh_dataset_inews/__init__.py
zh_dataset_inews/dataset.py
zh_dataset_inews/dev.pkl
zh_dataset_inews/test.pkl
zh_dataset_inews/test.py
zh_dataset_inews/train.pkl
zh_dataset_inews/version.txt
zh_dataset_inews-0.0.2.dist-info/LICENSE
zh_dataset_inews-0.0.2.dist-info/METADATA
zh_dataset_inews-0.0.2.dist-info/WHEEL
zh_dataset_inews-0.0.2.dist-info/top_level.txt
zh_dataset_inews-0.0.2.dist-info/RECORD
