Metadata-Version: 2.1
Name: zh-dataset-inews
Version: 0.0.2
Summary: NLP tool
Home-page: https://github.com/deepdialog/zh-dataset-inews
Author: deepdialog
Author-email: thebotbot@sina.com
License: Private
Keywords: pip,text,NLP
Platform: any
